RapeSegmentation/__init__.py
RapeSegmentation/inference.py
RapeSegmentation/config/GID.yaml
RapeSegmentation/config/__init__.py
RapeSegmentation/config/a.py
RapeSegmentation/config/default.py
RapeSegmentation/config/default_test.py
RapeSegmentation/dataset/SlidingWindowDataset.py
RapeSegmentation/dataset/__init__.py
RapeSegmentation/model/__init__.py
RapeSegmentation/model/SwinUNet/__init__.py
RapeSegmentation/model/SwinUNet/swin_transformer_unet_skip_expand_decoder_sys.py
RapeSegmentation/model/SwinUNet/vision_transformer.py
RapeSegmentation/utils/__init__.py
RapeSegmentation/utils/convert2uint8.py
RapeSegmentation/utils/segment.py
RapeSegmentation/utils/test.py
RapeSegmentation/utils/utils.py
RapeSegmentation-0.1.13.dist-info/METADATA
RapeSegmentation-0.1.13.dist-info/WHEEL
RapeSegmentation-0.1.13.dist-info/top_level.txt
RapeSegmentation-0.1.13.dist-info/RECORD
